[
    {
        "title": "Review Panelist, Reviewer",
        "y1": "2017",
        "y2": "present",
        "other": "NSF AAG, NASA ADAP, NASA FINESST"
    },
    {
        "title": "Referee",
        "y1": "2012",
        "y2": "present",
        "other": "ApJ, MNRAS, JOSS, RASTI, NatA, A&A, OJAp"
    },
    {
        "title": "Coordinator",
        "y1": "2023",
        "y2": "present",
        "other": "Daily Astro Coffee at Princeton University"
    },
    {
        "title": "Organizer",
        "y1": "2026",
        "y2": "",
        "other": "Unifying Cosmic-Ray Research: Connecting Astroparticle Phenomenology with Advanced Theories, Simulations, and Observations"
    },
    {
        "title": "Organizer",
        "y1": "2024",
        "y2": "present",
        "other": "Star Formation/ISM Rendezvous Seminars at Princeton University"
    }
]